{
  "$schema": "https://raw.githubusercontent.com/streetsidesoftware/cspell/main/cspell.schema.json",
  "version": "0.2",
  "language": "en",
  "useGitignore": true,
  "ignorePaths": [
    "**/*.csv",
    "**/*.eex",
    "**/*.yml",
    "config",
    "assets",
    "mix.exs",
    "priv",
    "test"
  ],
  "words": [
    "AEXAMPLE",
    "BUCKETPOLICY",
    "FABBEXAMPLE",
    "Mjml",
    "ROOTFS",
    "Spex",
    "Ueberauth",
    "acreateserial",
    "anotherdummytoken",
    "behaviours",
    "cacertfile",
    "cacerts",
    "carstens",
    "castore",
    "checkmark",
    "circuitboard",
    "clickhouse",
    "clipcopy",
    "comeonin",
    "conzole",
    "describedby",
    "dialyxir",
    "distro",
    "dpkg",
    "dropzone",
    "dyno",
    "ecto",
    "enctype",
    "enoent",
    "esbuild",
    "evenodd",
    "extname",
    "extralight",
    "extn",
    "filelib",
    "firmwares",
    "fkey",
    "fullsweep",
    "fwup",
    "gencert",
    "geocoder",
    "geodata",
    "geoip",
    "getopts",
    "getstat",
    "haspopup",
    "healthz",
    "heroicons",
    "hexpm",
    "hljs",
    "hmac",
    "hostable",
    "ilike",
    "initca",
    "inotify",
    "invalidtoken",
    "ipfamily",
    "jitp",
    "joshk",
    "kalderimis",
    "keyfind",
    "labelledby",
    "latlng",
    "libcluster",
    "libncurses",
    "libstdc",
    "linecap",
    "linejoin",
    "liveview",
    "localtime",
    "logfmt",
    "logfmt",
    "maint",
    "mapbox",
    "maxlength",
    "memsup",
    "memset",
    "metas",
    "minlength",
    "mjml",
    "mybucket",
    "mynerveshub",
    "nerveshub",
    "nerveshubweb",
    "newz",
    "noformat",
    "nokey",
    "nomnomnom",
    "noninteractive",
    "noopener",
    "noreferrer",
    "novalidate",
    "nowrap",
    "nshoes",
    "ntoa",
    "oban",
    "oestrich",
    "optgroup",
    "peercert",
    "peername",
    "pids",
    "pkix",
    "postgrex",
    "progressbar",
    "psql",
    "rebar",
    "registered",
    "rgba",
    "sendfile",
    "setopts",
    "settingz",
    "sharedsecret",
    "sname",
    "sockname",
    "spex",
    "ssljson",
    "statsd",
    "strftime",
    "stylesheet",
    "successfuls",
    "swaggerui",
    "tabindex",
    "tabnav",
    "tlsv",
    "topbar",
    "tracestate",
    "tzdata",
    "Ueberauth",
    "ueberauth",
    "undigits",
    "unprovisioned",
    "validtoken",
    "xdelta"
  ]
}
